tree_detection_framework/__init__.py
tree_detection_framework/constants.py
tree_detection_framework/detection/SAM2_detector.py
tree_detection_framework/detection/__init__.py
tree_detection_framework/detection/detector.py
tree_detection_framework/detection/models.py
tree_detection_framework/detection/region_detections.py
tree_detection_framework/entrypoints/__init__.py
tree_detection_framework/entrypoints/generate_predictions.py
tree_detection_framework/entrypoints/tile_data.py
tree_detection_framework/evaluation/__init__.py
tree_detection_framework/postprocessing/__init__.py
tree_detection_framework/postprocessing/postprocessing.py
tree_detection_framework/preprocessing/__init__.py
tree_detection_framework/preprocessing/derived_geodatasets.py
tree_detection_framework/preprocessing/preprocessing.py
tree_detection_framework/utils/__init__.py
tree_detection_framework/utils/detection.py
tree_detection_framework/utils/geometric.py
tree_detection_framework/utils/geospatial.py
tree_detection_framework/utils/raster.py
tree_detection_framework-0.1.0.dist-info/LICENSE
tree_detection_framework-0.1.0.dist-info/METADATA
tree_detection_framework-0.1.0.dist-info/WHEEL
tree_detection_framework-0.1.0.dist-info/RECORD
