Metadata-Version: 2.3
Name: tree-detection-framework
Version: 0.1.0
Summary: Framework for detecting trees in remote sensing data
License: BSD-3
Author: David Russell
Author-email: djrussell@ucdavis.edu
Requires-Python: >=3.10,<3.12
Classifier: License :: Other/Proprietary License
Classifier: Programming Language :: Python :: 3
Classifier: Programming Language :: Python :: 3.10
Classifier: Programming Language :: Python :: 3.11
Requires-Dist: deepforest (>=1.3.3,<2.0.0)
Requires-Dist: ipykernel (>=6.29.5,<7.0.0)
Requires-Dist: polygonenms-ofo-fork (>=0.1.0,<0.2.0)
Requires-Dist: torchgeo (>=0.6.0,<0.7.0)
